fsrs/__init__.py
fsrs/card.py
fsrs/optimizer.py
fsrs/review_log.py
fsrs/scheduler.py
fsrs-6.1.1.dist-info/licenses/LICENSE
fsrs-6.1.1.dist-info/METADATA
fsrs-6.1.1.dist-info/WHEEL
fsrs-6.1.1.dist-info/top_level.txt
fsrs-6.1.1.dist-info/RECORD
