Metadata-Version: 2.4
Name: fsrs
Version: 6.1.1
Summary: Free Spaced Repetition Scheduler
Author-email: Jarrett Ye <jarrett.ye@outlook.com>, Joshua Hamilton <hamiltonjoshuadavid@gmail.com>
License: MIT License
Project-URL: Homepage, https://github.com/open-spaced-repetition/py-fsrs
Keywords: spaced-repetition,flashcard
Classifier: License :: OSI Approved :: MIT License
Classifier: Programming Language :: Python :: 3
Requires-Python: >=3.10
License-File: LICENSE
Provides-Extra: dev
Requires-Dist: pytest; extra == "dev"
Requires-Dist: ruff; extra == "dev"
Requires-Dist: setuptools; extra == "dev"
Requires-Dist: torch; extra == "dev"
Requires-Dist: numpy; extra == "dev"
Requires-Dist: pandas; extra == "dev"
Requires-Dist: uv; extra == "dev"
Requires-Dist: pytest-xdist; extra == "dev"
Requires-Dist: pdoc; extra == "dev"
Requires-Dist: tqdm; extra == "dev"
Requires-Dist: pytest-cov; extra == "dev"
Provides-Extra: optimizer
Requires-Dist: torch; extra == "optimizer"
Requires-Dist: numpy; extra == "optimizer"
Requires-Dist: pandas; extra == "optimizer"
Requires-Dist: tqdm; extra == "optimizer"
Dynamic: license-file
